relia/__init__.py
relia/cli.py
relia/core/__init__.py
relia/core/advisor.py
relia/core/bundled_pricing.db
relia/core/cache.py
relia/core/config.py
relia/core/constants.py
relia/core/engine.py
relia/core/matcher.py
relia/core/parser.py
relia/core/pricing.py
relia/core/usage.py
relia/main.py
relia/models.py
relia/utils/__init__.py
relia/utils/logger.py
relia/utils/output.py
relia_oss-1.3.2.dist-info/METADATA
relia_oss-1.3.2.dist-info/WHEEL
relia_oss-1.3.2.dist-info/entry_points.txt
relia_oss-1.3.2.dist-info/licenses/LICENSE
relia_oss-1.3.2.dist-info/RECORD
