Metadata-Version: 2.4
Name: relia_oss
Version: 1.3.2
Summary: Cloud cost prevention and optimization tool.
License-File: LICENSE
Keywords: finops,terraform,cost,cloud,aws
Author: David Ahmann
Author-email: dahmann@lumyn.cc
Requires-Python: >=3.10,<4.0
Classifier: Development Status :: 4 - Beta
Classifier: Environment :: Console
Classifier: Intended Audience :: Developers
Classifier: Intended Audience :: Information Technology
Classifier: License :: OSI Approved :: Apache Software License
Classifier: Operating System :: OS Independent
Classifier: Programming Language :: Python :: 3
Classifier: Programming Language :: Python :: 3.10
Classifier: Programming Language :: Python :: 3.11
Classifier: Programming Language :: Python :: 3.12
Classifier: Programming Language :: Python :: 3.13
Classifier: Programming Language :: Python :: 3.14
Classifier: Topic :: Software Development :: Quality Assurance
Classifier: Topic :: Utilities
Requires-Dist: boto3 (>=1.42.4,<2.0.0)
Requires-Dist: pydantic (>=2.0.0,<3.0.0)
Requires-Dist: pydantic-settings (>=2.0.0,<3.0.0)
Requires-Dist: python-hcl2 (>=7.3.1,<8.0.0)
Requires-Dist: pyyaml (>=6.0.3,<7.0.0)
Requires-Dist: rich (>=13.0.0,<14.0.0)
Requires-Dist: typer (>=0.20.0,<0.21.0)
Project-URL: Homepage, https://github.com/davidahmann/relia_oss
Project-URL: Repository, https://github.com/davidahmann/relia_oss
